CHANGES.txt
LICENSE.txt
MANIFEST.in
README.txt
setup.py
GpxImageLinkifier/__init__.py
GpxImageLinkifier/gil.py
GpxImageLinkifier.egg-info/PKG-INFO
GpxImageLinkifier.egg-info/SOURCES.txt
GpxImageLinkifier.egg-info/dependency_links.txt
GpxImageLinkifier.egg-info/entry_points.txt
GpxImageLinkifier.egg-info/requires.txt
GpxImageLinkifier.egg-info/top_level.txt
GpxImageLinkifier/test/__init__.py
GpxImageLinkifier/test/test_GpxImageLinkifier.py