Metadata-Version: 1.0
Name: GpxImageLinkifier
Version: 0.1.1
Summary: Links GPX tracks to photographs by matching the image timestamp (in the EXIF data) to the timestamp in the GPX track supplied.
Home-page: https://pypi.python.org/pypi/GpxImageLinkifier
Author: Austin Happel
Author-email: austin@austinhappel.com
License: LICENSE.txt
Platform: UNKNOWN
Classifier: Programming Language :: Python :: 2.7
Classifier: Environment :: Console
Classifier: License :: OSI Approved :: GNU General Public License v3 or later (GPLv3+)
